ligandparam/__init__.py
ligandparam/driver.py
ligandparam/interfaces.py
ligandparam/log.py
ligandparam/parametrization.py
ligandparam/utils.py
ligandparam/cli/__init__.py
ligandparam/cli/cli_lighfix.py
ligandparam/cli/ligandparam_getparam.py
ligandparam/cli/mol2_to_sage.py
ligandparam/cli/smiles_to_pdb.py
ligandparam/deprecated/stagegausrotation.py
ligandparam/deprecated/stagegaussian.py
ligandparam/deprecated/stagegaussiantomol2.py
ligandparam/deprecated/stageinitialize.py
ligandparam/deprecated/stagelazyresp.py
ligandparam/deprecated/stageleap.py
ligandparam/deprecated/stagenormalizecharges.py
ligandparam/deprecated/stageparmchk.py
ligandparam/io/__init__.py
ligandparam/io/coordinates.py
ligandparam/io/gaussianIO.py
ligandparam/io/leapIO.py
ligandparam/io/smiles.py
ligandparam/multiresp/__init__.py
ligandparam/multiresp/endstate.py
ligandparam/multiresp/functions.py
ligandparam/multiresp/intermolequiv.py
ligandparam/multiresp/mdinutils.py
ligandparam/multiresp/parmhelper.py
ligandparam/multiresp/residueresp.py
ligandparam/multiresp/respfunctions.py
ligandparam/recipes/__init__.py
ligandparam/recipes/buildligand.py
ligandparam/recipes/dpfreeligand.py
ligandparam/recipes/dplazyligand.py
ligandparam/recipes/freeligand.py
ligandparam/recipes/lazierligand.py
ligandparam/recipes/lazyligand.py
ligandparam/recipes/optligand.py
ligandparam/recipes/rnaligand.py
ligandparam/stages/__init__.py
ligandparam/stages/abstractstage.py
ligandparam/stages/build_system.py
ligandparam/stages/charge.py
ligandparam/stages/deepmd.py
ligandparam/stages/displacemol.py
ligandparam/stages/gaussian.py
ligandparam/stages/generate_sage_params.py
ligandparam/stages/initialize.py
ligandparam/stages/leap.py
ligandparam/stages/lighfix.py
ligandparam/stages/parmchk.py
ligandparam/stages/pdb_names.py
ligandparam/stages/resp.py
ligandparam/stages/sdfconverters.py
ligandparam/stages/smilestopdb.py
ligandparam/stages/teststage.py
ligandparam/stages/typematching.py
ligandparam/stages/utilsstages.py
ligandparam-0.3.5.dist-info/METADATA
ligandparam-0.3.5.dist-info/WHEEL
ligandparam-0.3.5.dist-info/entry_points.txt
ligandparam-0.3.5.dist-info/top_level.txt
ligandparam-0.3.5.dist-info/RECORD
